potracecffi
