Metadata-Version: 2.1
Name: potracecffi
Version: 2022.8.22.post1
Summary: Minimal bindings to potracelib using cffi
Home-page: https://github.com/wntrblm/potracecffi
Author: Alethea Katherine Flowers
Author-email: thea@winterbloom.com
Project-URL: Source, https://github.com/wntrblm/potracecffi
Classifier: Intended Audience :: Developers
Classifier: Topic :: Software Development :: Build Tools
Classifier: License :: OSI Approved :: MIT License
Classifier: Programming Language :: Python :: 3
Classifier: Programming Language :: Python :: 3.10
License-File: LICENSE
